README.txt
setup.cfg
setup.py
bin/arp-enumerate
bin/ipaddress
bin/ipv4-address-classes
bin/mac-vendor-lookup
bin/network-enumerate
bin/network-split
bin/reverse-lookup
bin/route-lookup
bin/seine-netstat-statistics
bin/seine-tldcache
bin/snmp-ifstatus
bin/snmp-processes
bin/sort-addresslist
seine/__init__.py
seine/address.py
seine/classes.py
seine/netstat.py
seine/network.py
seine/oui.py
seine/ping.py
seine/proxyconfig.py
seine/route.py
seine/url.py
seine.egg-info/PKG-INFO
seine.egg-info/SOURCES.txt
seine.egg-info/dependency_links.txt
seine.egg-info/requires.txt
seine.egg-info/top_level.txt
seine/dns/__init__.py
seine/dns/authservers.py
seine/dns/delegation.py
seine/dns/resolver.py
seine/dns/rootservers.py
seine/dns/tld.py
seine/platform/__init__.py
seine/platform/bsd/__init__.py
seine/platform/bsd/network.py
seine/platform/linux/__init__.py
seine/platform/linux/network.py
seine/snmp/__init__.py
seine/snmp/agent.py
seine/snmp/client.py
seine/snmp/script.py
seine/snmp/devices/__init__.py
seine/snmp/devices/process.py
seine/snmp/devices/network/__init__.py
seine/snmp/devices/network/interfaces.py
seine/snmp/devices/printers/__init__.py
seine/snmp/devices/printers/hp.py
seine/whois/__init__.py
seine/whois/arin.py
seine/whois/cache.py
seine/whois/client.py
seine/whois/parsers.py
seine/whois/formats/__init__.py
seine/whois/formats/ficora.py
seine/whois/formats/gtld.py
seine/whois/formats/nominet.py
seine/whois/formats/saudinic.py