Metadata-Version: 1.0
Name: seine
Version: 3.2.0
Summary: Various network address and url related utilities
Home-page: https://github.com/hile/seine
Author: Ilkka Tuohela
Author-email: hile@iki.fi
License: PSF
Keywords: network utility scripts and classes for python
Platform: UNKNOWN
